[
  {
    "orderDate": "2025-05-24",
    "dueDate": "2025-05-30",
    "userId": 11,
    "cart": [
      {
        "id": 6,
        "category": "קונדיטוריה",
        "name": "עוגת קרוסלה",
        "description": "עוגת גזר עם אגוזים וקינמון",
        "image": "CarouselCake.jpg",
        "content": "גזר מגורר, אגוזים, קמח, קינמון",
        "price": 36,
        "quantity": 2
      },
      {
        "id": 5,
        "category": "קונדיטוריה",
        "name": "שלושה שוקולדים",
        "description": "עוגת גבינה אפויה ונימוחה",
        "image": "ThreeChocolates.jpg",
        "content": "גבינת שמנת, ביצים, סוכר",
        "price": 42,
        "quantity": 1
      }
    ],
    "id": 3
  },
  {
    "orderDate": "2025-05-24",
    "dueDate": "2025-05-30",
    "userId": 11,
    "cart": [
      {
        "id": 16,
        "category": "קונדיטוריה",
        "name": "עוגת שלגיה",
        "description": "עוגייה פריכה עם שוקולד צ'יפס איכותי",
        "image": "SnowWhitecake.jpg",
        "content": "קמח, סוכר, חמאה, שוקולד צ'יפס",
        "price": "10",
        "quantity": 1
      }
    ],
    "id": 4
  },
  {
    "orderDate": "2025-05-24",
    "dueDate": "2025-05-30",
    "userId": 11,
    "cart": [
      {
        "id": 16,
        "category": "קונדיטוריה",
        "name": "עוגת שלגיה",
        "description": "עוגייה פריכה עם שוקולד צ'יפס איכותי",
        "image": "SnowWhitecake.jpg",
        "content": "קמח, סוכר, חמאה, שוקולד צ'יפס",
        "price": "10",
        "quantity": 1
      }
    ],
    "id": 5
  },
  {
    "orderDate": "2025-05-24",
    "dueDate": "2025-05-30",
    "userId": 11,
    "cart": [
      {
        "id": 2,
        "category": "קונדיטוריה",
        "name": "קרמבולינה",
        "description": "עוגייה קלאסית נמסה בפה",
        "image": "cramboline.jpg",
        "content": "קמח, חמאה, סוכר וניל",
        "price": "15",
        "quantity": 1
      }
    ],
    "id": 6
  },
  {
    "orderDate": "2025-05-24",
    "dueDate": "2025-05-30",
    "userId": 13,
    "cart": [
      {
        "id": 20,
        "category": "קייטרינג",
        "name": "פסטה בטטה ושמנת",
        "description": "מאפה אישי רך עם זיתים",
        "image": "SweetPotatoCreamPasta.jpg",
        "content": "קמח, שמרים, זיתים, שמן זית",
        "price": 7,
        "quantity": 1
      }
    ],
    "id": 7
  },
  {
    "orderDate": "2025-05-24",
    "dueDate": "2025-05-31",
    "userId": 11,
    "cart": [
      {
        "id": 15,
        "category": "קונדיטוריה",
        "name": "עוגת בלרינה",
        "description": "עוגייה פריכה עם חמאת בוטנים",
        "image": "BallerinaCake.jpg",
        "content": "קמח, חמאת בוטנים, ביצה",
        "price": "100",
        "quantity": 5
      },
      {
        "id": 20,
        "category": "קייטרינג",
        "name": "פסטה בטטה ושמנת",
        "description": "מאפה אישי רך עם זיתים",
        "image": "SweetPotatoCreamPasta.jpg",
        "content": "קמח, שמרים, זיתים, שמן זית",
        "price": 7,
        "quantity": 1
      }
    ],
    "id": 8
  },
  {
    "orderDate": "2025-05-24",
    "dueDate": "2025-05-30",
    "userId": 11,
    "cart": [
      {
        "id": 15,
        "category": "קונדיטוריה",
        "name": "עוגת בלרינה",
        "description": "עוגייה פריכה עם חמאת בוטנים",
        "image": "BallerinaCake.jpg",
        "content": "קמח, חמאת בוטנים, ביצה",
        "price": "55",
        "quantity": 1
      }
    ],
    "id": 9
  },
  {
    "orderDate": "2025-05-24",
    "dueDate": "2025-05-30",
    "userId": 14,
    "cart": [
      {
        "id": 15,
        "category": "קונדיטוריה",
        "name": "עוגת בלרינה",
        "description": "עוגייה פריכה עם חמאת בוטנים",
        "image": "BallerinaCake.jpg",
        "content": "קמח, חמאת בוטנים, ביצה",
        "price": "55",
        "quantity": 1
      }
    ],
    "id": 10
  },
  {
    "orderDate": "2025-05-25",
    "dueDate": "2025-06-06",
    "userId": 15,
    "cart": [
      {
        "id": 15,
        "category": "קונדיטוריה",
        "name": "עוגת בלרינה",
        "description": "עוגייה פריכה עם חמאת בוטנים",
        "image": "BallerinaCake.jpg",
        "content": "קמח, חמאת בוטנים, ביצה",
        "price": "55",
        "quantity": 2
      }
    ],
    "id": 11
  },
  {
    "orderDate": "2025-05-25",
    "dueDate": "2025-05-31",
    "userId": 16,
    "cart": [
      {
        "id": 8,
        "category": "קייטרינג",
        "name": "אורז אושפלאו",
        "description": "קרואסון טרי עם שוקולד בפנים",
        "image": "OshfloRice.jpg",
        "content": "בצק שמרים, שוקולד, חמאה",
        "price": 9,
        "quantity": 2
      }
    ],
    "id": 12
  },
  {
    "orderDate": "2025-05-25",
    "dueDate": "2025-06-01",
    "userId": 11,
    "cart": [
      {
        "id": 15,
        "category": "קונדיטוריה",
        "name": "עוגת בלרינה",
        "description": "עוגייה פריכה עם חמאת בוטנים",
        "image": "BallerinaCake.jpg",
        "content": "קמח, חמאת בוטנים, ביצה",
        "price": "55",
        "quantity": 3
      }
    ],
    "id": 13
  },
  {
    "orderDate": "2025-06-19",
    "dueDate": "2025-07-02",
    "userId": 17,
    "cart": [
      {
        "id": 15,
        "category": "קונדיטוריה",
        "name": "עוגת בלרינה",
        "description": "עוגייה פריכה עם חמאת בוטנים",
        "image": "BallerinaCake.jpg",
        "content": "קמח, חמאת בוטנים, ביצה",
        "price": "55",
        "quantity": 2
      },
      {
        "id": 13,
        "category": "מגשי ארוח",
        "name": "מתוק משפחתי",
        "description": "סוכריות לעיסה בטעמים שונים",
        "image": "FamilySweet.jpg",
        "content": "סוכר, חלב, טעמים טבעיים",
        "price": 4,
        "quantity": 1
      }
    ],
    "id": 14
  }
]